{
  "description": "Mapping of regions to their sensitivity levels for each framework. Levels: VERY_HIGH, HIGH, MEDIUM, LOW, NEUTRAL.",
  "matrix": {
    "USA": {
      "islamic_compliance": "LOW",
      "judeo_christian_compliance": "MEDIUM",
      "hindu_buddhist_compliance": "LOW",
      "lgbtq_acceptance": "HIGH",
      "gender_roles_feminism": "HIGH",
      "political_speech_censorship": "LOW",
      "historical_grievances": "HIGH",
      "social_caste_hierarchy": "LOW",
      "environmentalism_sustainability": "MEDIUM",
      "body_image_positivity": "HIGH",
      "racial_ethnic_sensitivity": "VERY_HIGH"
    },
    "China": {
      "islamic_compliance": "MEDIUM",
      "judeo_christian_compliance": "LOW",
      "hindu_buddhist_compliance": "HIGH",
      "lgbtq_acceptance": "LOW",
      "gender_roles_feminism": "MEDIUM",
      "political_speech_censorship": "VERY_HIGH",
      "historical_grievances": "HIGH",
      "social_caste_hierarchy": "MEDIUM",
      "environmentalism_sustainability": "MEDIUM",
      "body_image_positivity": "LOW",
      "racial_ethnic_sensitivity": "MEDIUM"
    },
    "Japan": {
      "islamic_compliance": "LOW",
      "judeo_christian_compliance": "LOW",
      "hindu_buddhist_compliance": "HIGH",
      "lgbtq_acceptance": "MEDIUM",
      "gender_roles_feminism": "MEDIUM",
      "political_speech_censorship": "LOW",
      "historical_grievances": "HIGH",
      "social_caste_hierarchy": "LOW",
      "environmentalism_sustainability": "MEDIUM",
      "body_image_positivity": "MEDIUM",
      "racial_ethnic_sensitivity": "LOW"
    },
    "Germany": {
      "islamic_compliance": "MEDIUM",
      "judeo_christian_compliance": "MEDIUM",
      "hindu_buddhist_compliance": "LOW",
      "lgbtq_acceptance": "HIGH",
      "gender_roles_feminism": "HIGH",
      "political_speech_censorship": "LOW",
      "historical_grievances": "VERY_HIGH",
      "social_caste_hierarchy": "LOW",
      "environmentalism_sustainability": "HIGH",
      "body_image_positivity": "MEDIUM",
      "racial_ethnic_sensitivity": "HIGH"
    },
    "United Kingdom": {
      "islamic_compliance": "MEDIUM",
      "judeo_christian_compliance": "MEDIUM",
      "hindu_buddhist_compliance": "MEDIUM",
      "lgbtq_acceptance": "HIGH",
      "gender_roles_feminism": "HIGH",
      "political_speech_censorship": "LOW",
      "historical_grievances": "HIGH",
      "social_caste_hierarchy": "HIGH",
      "environmentalism_sustainability": "HIGH",
      "body_image_positivity": "HIGH",
      "racial_ethnic_sensitivity": "HIGH"
    },
    "India": {
      "islamic_compliance": "HIGH",
      "judeo_christian_compliance": "MEDIUM",
      "hindu_buddhist_compliance": "VERY_HIGH",
      "lgbtq_acceptance": "MEDIUM",
      "gender_roles_feminism": "MEDIUM",
      "political_speech_censorship": "HIGH",
      "historical_grievances": "HIGH",
      "social_caste_hierarchy": "VERY_HIGH",
      "environmentalism_sustainability": "MEDIUM",
      "body_image_positivity": "LOW",
      "racial_ethnic_sensitivity": "HIGH"
    },
    "Brazil": {
      "islamic_compliance": "LOW",
      "judeo_christian_compliance": "HIGH",
      "hindu_buddhist_compliance": "LOW",
      "lgbtq_acceptance": "HIGH",
      "gender_roles_feminism": "MEDIUM",
      "political_speech_censorship": "MEDIUM",
      "historical_grievances": "MEDIUM",
      "social_caste_hierarchy": "HIGH",
      "environmentalism_sustainability": "HIGH",
      "body_image_positivity": "HIGH",
      "racial_ethnic_sensitivity": "HIGH"
    },
    "Saudi Arabia": {
      "islamic_compliance": "VERY_HIGH",
      "judeo_christian_compliance": "MEDIUM",
      "hindu_buddhist_compliance": "LOW",
      "lgbtq_acceptance": "VERY_HIGH",
      "gender_roles_feminism": "VERY_HIGH",
      "political_speech_censorship": "HIGH",
      "historical_grievances": "LOW",
      "social_caste_hierarchy": "MEDIUM",
      "environmentalism_sustainability": "LOW",
      "body_image_positivity": "VERY_HIGH",
      "racial_ethnic_sensitivity": "LOW"
    },
    "Russia": {
      "islamic_compliance": "MEDIUM",
      "judeo_christian_compliance": "HIGH",
      "hindu_buddhist_compliance": "LOW",
      "lgbtq_acceptance": "VERY_HIGH",
      "gender_roles_feminism": "HIGH",
      "political_speech_censorship": "VERY_HIGH",
      "historical_grievances": "HIGH",
      "social_caste_hierarchy": "LOW",
      "environmentalism_sustainability": "LOW",
      "body_image_positivity": "LOW",
      "racial_ethnic_sensitivity": "MEDIUM"
    },
    "Nigeria": {
      "islamic_compliance": "HIGH",
      "judeo_christian_compliance": "HIGH",
      "hindu_buddhist_compliance": "LOW",
      "lgbtq_acceptance": "VERY_HIGH",
      "gender_roles_feminism": "HIGH",
      "political_speech_censorship": "MEDIUM",
      "historical_grievances": "HIGH",
      "social_caste_hierarchy": "MEDIUM",
      "environmentalism_sustainability": "LOW",
      "body_image_positivity": "MEDIUM",
      "racial_ethnic_sensitivity": "HIGH"
    },
    "Nordic Europe": {
      "islamic_compliance": "MEDIUM",
      "judeo_christian_compliance": "LOW",
      "hindu_buddhist_compliance": "LOW",
      "lgbtq_acceptance": "LOW",
      "gender_roles_feminism": "LOW",
      "political_speech_censorship": "LOW",
      "historical_grievances": "LOW",
      "social_caste_hierarchy": "LOW",
      "environmentalism_sustainability": "HIGH",
      "body_image_positivity": "MEDIUM",
      "racial_ethnic_sensitivity": "MEDIUM"
    },
    "MENA": {
      "islamic_compliance": "VERY_HIGH",
      "judeo_christian_compliance": "HIGH",
      "hindu_buddhist_compliance": "LOW",
      "lgbtq_acceptance": "VERY_HIGH",
      "gender_roles_feminism": "HIGH",
      "political_speech_censorship": "HIGH",
      "historical_grievances": "MEDIUM",
      "social_caste_hierarchy": "MEDIUM",
      "environmentalism_sustainability": "LOW",
      "body_image_positivity": "HIGH",
      "racial_ethnic_sensitivity": "MEDIUM"
    },
    "Confucian Asia": {
        "islamic_compliance": "LOW",
        "judeo_christian_compliance": "LOW",
        "hindu_buddhist_compliance": "HIGH",
        "lgbtq_acceptance": "MEDIUM",
        "gender_roles_feminism": "MEDIUM",
        "political_speech_censorship": "HIGH",
        "historical_grievances": "HIGH",
        "social_caste_hierarchy": "MEDIUM",
        "environmentalism_sustainability": "MEDIUM",
        "body_image_positivity": "LOW",
        "racial_ethnic_sensitivity": "LOW"
    }
  }
}
